vcfphasesets
